aliyunsdksddp/__init__.py
aliyunsdksddp/endpoint.py
aliyunsdksddp/request/__init__.py
aliyunsdksddp/request/v20190103/CreateConfigRequest.py
aliyunsdksddp/request/v20190103/CreateDataLimitRequest.py
aliyunsdksddp/request/v20190103/CreateRuleRequest.py
aliyunsdksddp/request/v20190103/CreateScanTaskRequest.py
aliyunsdksddp/request/v20190103/CreateSlrRoleRequest.py
aliyunsdksddp/request/v20190103/DeleteDataLimitRequest.py
aliyunsdksddp/request/v20190103/DeleteRuleRequest.py
aliyunsdksddp/request/v20190103/DescribeCategoryTemplateListRequest.py
aliyunsdksddp/request/v20190103/DescribeCategoryTemplateRuleListRequest.py
aliyunsdksddp/request/v20190103/DescribeColumnsRequest.py
aliyunsdksddp/request/v20190103/DescribeColumnsV2Request.py
aliyunsdksddp/request/v20190103/DescribeConfigsRequest.py
aliyunsdksddp/request/v20190103/DescribeDataAssetsRequest.py
aliyunsdksddp/request/v20190103/DescribeDataLimitDetailRequest.py
aliyunsdksddp/request/v20190103/DescribeDataLimitSetRequest.py
aliyunsdksddp/request/v20190103/DescribeDataLimitsRequest.py
aliyunsdksddp/request/v20190103/DescribeDataMaskingRunHistoryRequest.py
aliyunsdksddp/request/v20190103/DescribeDataMaskingTasksRequest.py
aliyunsdksddp/request/v20190103/DescribeDataObjectColumnDetailRequest.py
aliyunsdksddp/request/v20190103/DescribeDataObjectColumnDetailV2Request.py
aliyunsdksddp/request/v20190103/DescribeDataObjectsRequest.py
aliyunsdksddp/request/v20190103/DescribeDocTypesRequest.py
aliyunsdksddp/request/v20190103/DescribeEventDetailRequest.py
aliyunsdksddp/request/v20190103/DescribeEventTypesRequest.py
aliyunsdksddp/request/v20190103/DescribeEventsRequest.py
aliyunsdksddp/request/v20190103/DescribeInstanceSourcesRequest.py
aliyunsdksddp/request/v20190103/DescribeInstancesRequest.py
aliyunsdksddp/request/v20190103/DescribeOssObjectDetailRequest.py
aliyunsdksddp/request/v20190103/DescribeOssObjectDetailV2Request.py
aliyunsdksddp/request/v20190103/DescribeOssObjectsRequest.py
aliyun_python_sdk_sddp-1.0.10.dist-info/LICENSE
aliyun_python_sdk_sddp-1.0.10.dist-info/METADATA
aliyun_python_sdk_sddp-1.0.10.dist-info/WHEEL
aliyun_python_sdk_sddp-1.0.10.dist-info/top_level.txt
aliyun_python_sdk_sddp-1.0.10.dist-info/RECORD
